{
  "items": [
    { "date": "2026-1-17", "text": "<a href=\"https://xgsun.mysxl.cn\" target=\"_blank\" rel=\"noopener\">Dr. Xiangguo SUN</a> will serve as SPC for IJCAI 2026 and SIGIR 2026." },
    { "date": "2025-11-15", "text": "<a href=\"https://xgsun.mysxl.cn\" target=\"_blank\" rel=\"noopener\">Dr. Xiangguo SUN</a> is set to join Southeast University in Jan 2026 as a Full Professor." }
    ],
  "old":[
    { "date": "2025-10-23", "text": "CIT @ ROMA Lab (ROMA Lab Cultural Insight Test) version 4.3 released." },
    { "date": "2025-10-17", "text": "Dr. Xiangguo SUN was awarded NeurIPS'2025 Top Reviewer." },
    { "date": "2025-10-15", "text": "Dr. Xiangguo Sun has been appointed to a dual leadership role at CAAI: Deputy Secretary-General for Social Computing and Social Intelligence, and Chair of the new Rising Scholars Committee." },
    { "date": "2025-10-13", "text": "Our Lab website established!" }
  ]
}





